cli/__init__.py
cli/kafka_config.py
cli/show_status.py
cli/start_file_writer.py
cli/stop_file_writer.py
file_writer_control/CommandChannel.py
file_writer_control/CommandHandler.py
file_writer_control/CommandStatus.py
file_writer_control/InThreadStatusTracker.py
file_writer_control/JobHandler.py
file_writer_control/JobStatus.py
file_writer_control/KafkaTopicUrl.py
file_writer_control/StateExtractor.py
file_writer_control/WorkerFinder.py
file_writer_control/WorkerJobPool.py
file_writer_control/WorkerStatus.py
file_writer_control/WriteJob.py
file_writer_control/__init__.py
file_writer_control/_version.py
file_writer_control-1.3.0.dist-info/LICENSE
file_writer_control-1.3.0.dist-info/METADATA
file_writer_control-1.3.0.dist-info/WHEEL
file_writer_control-1.3.0.dist-info/entry_points.txt
file_writer_control-1.3.0.dist-info/top_level.txt
file_writer_control-1.3.0.dist-info/RECORD
