Metadata-Version: 2.1
Name: file-writer-control
Version: 1.3.0
Summary: A small Python library for controlling the ESS kafka-to-nexus file-writer.
Home-page: https://github.com/ess-dmsc/file_writer_control
Author: ScreamingUdder
License: BSD 2-Clause License
Requires-Python: >=3.6.0
License-File: LICENSE
Requires-Dist: kafka-python (>=2.0)
Requires-Dist: ess-streaming-data-types (>=0.14.0)
